README.rst
setup.py
graphql_client/__init__.py
graphql_client/client.py
graphql_client.egg-info/PKG-INFO
graphql_client.egg-info/SOURCES.txt
graphql_client.egg-info/dependency_links.txt
graphql_client.egg-info/requires.txt
graphql_client.egg-info/top_level.txt