Metadata-Version: 1.0
Name: graphql-client
Version: 0.3.0
Summary: A GraphQL Client
Home-page: https://github.com/hsdp/python-graphql-client.git
Author: Kevin Smithson
Author-email: kevin.smithson@philips.com
License: Apache-2.0
Platform: UNKNOWN
